{
  "MIT/search-39" : {
    "transaction" : "MIT/search-39",
    "sampleCount" : 134,
    "errorCount" : 102,
    "errorPct" : 76.1194,
    "meanResTime" : 50138.80597014926,
    "medianResTime" : 797.5,
    "minResTime" : 97.0,
    "maxResTime" : 3094462.0,
    "pct1ResTime" : 9593.0,
    "pct2ResTime" : 30237.0,
    "pct3ResTime" : 3090678.5,
    "throughput" : 0.04246331597301995,
    "receivedKBytesPerSec" : 0.41977799003934196,
    "sentKBytesPerSec" : 0.05925046206584032
  },
  "Research/research-182-0" : {
    "transaction" : "Research/research-182-0",
    "sampleCount" : 105,
    "errorCount" : 0,
    "errorPct" : 0.0,
    "meanResTime" : 1038.5714285714287,
    "medianResTime" : 378.0,
    "minResTime" : 47.0,
    "maxResTime" : 17681.0,
    "pct1ResTime" : 2649.2000000000007,
    "pct2ResTime" : 4785.899999999995,
    "pct3ResTime" : 17076.799999999977,
    "throughput" : 0.34380464038034614,
    "receivedKBytesPerSec" : 0.23267247635115224,
    "sentKBytesPerSec" : 0.23938741073358086
  },
  "News/sites/default/files/styles/frontpage__featured_news/public/images/202411/ai-in-medicine.jpg-304" : {
    "transaction" : "News/sites/default/files/styles/frontpage__featured_news/public/images/202411/ai-in-medicine.jpg-304",
    "sampleCount" : 80,
    "errorCount" : 12,
    "errorPct" : 15.0,
    "meanResTime" : 2578.462499999999,
    "medianResTime" : 1358.5,
    "minResTime" : 117.0,
    "maxResTime" : 20654.0,
    "pct1ResTime" : 7535.300000000004,
    "pct2ResTime" : 8396.400000000001,
    "pct3ResTime" : 20654.0,
    "throughput" : 0.10316324293654171,
    "receivedKBytesPerSec" : 2.583415642287903,
    "sentKBytesPerSec" : 0.06860758636697745
  },
  "Research/research-182-1" : {
    "transaction" : "Research/research-182-1",
    "sampleCount" : 105,
    "errorCount" : 1,
    "errorPct" : 0.95238096,
    "meanResTime" : 33932.68571428571,
    "medianResTime" : 718.0,
    "minResTime" : 58.0,
    "maxResTime" : 3012633.0,
    "pct1ResTime" : 4750.0,
    "pct2ResTime" : 20366.999999999975,
    "pct3ResTime" : 2848080.2399999937,
    "throughput" : 0.033321718334371066,
    "receivedKBytesPerSec" : 0.4022512797523276,
    "sentKBytesPerSec" : 0.02301281172467502
  },
  "Research/themes/mit/assets/js/lazysizes.86d137a321e96feaa1d0.js-206" : {
    "transaction" : "Research/themes/mit/assets/js/lazysizes.86d137a321e96feaa1d0.js-206",
    "sampleCount" : 96,
    "errorCount" : 15,
    "errorPct" : 15.625,
    "meanResTime" : 1658.4687500000005,
    "medianResTime" : 436.5,
    "minResTime" : 52.0,
    "maxResTime" : 72050.0,
    "pct1ResTime" : 2490.9999999999995,
    "pct2ResTime" : 4918.249999999996,
    "pct3ResTime" : 72050.0,
    "throughput" : 0.20326623430244745,
    "receivedKBytesPerSec" : 1.4000358891944942,
    "sentKBytesPerSec" : 0.11453575897706268
  },
  "Research/files/images/201806/08_preview_1.jpeg-224" : {
    "transaction" : "Research/files/images/201806/08_preview_1.jpeg-224",
    "sampleCount" : 80,
    "errorCount" : 36,
    "errorPct" : 45.0,
    "meanResTime" : 2156.0125000000016,
    "medianResTime" : 1183.0,
    "minResTime" : 294.0,
    "maxResTime" : 14239.0,
    "pct1ResTime" : 4564.500000000003,
    "pct2ResTime" : 6735.250000000002,
    "pct3ResTime" : 14239.0,
    "throughput" : 0.0986370821178368,
    "receivedKBytesPerSec" : 14.566500812522964,
    "sentKBytesPerSec" : 0.059721670813533995
  },
  "MIT/q/climate%20chang?count=3-55" : {
    "transaction" : "MIT/q/climate%20chang?count=3-55",
    "sampleCount" : 129,
    "errorCount" : 21,
    "errorPct" : 16.27907,
    "meanResTime" : 291.6124031007753,
    "medianResTime" : 80.0,
    "minResTime" : 43.0,
    "maxResTime" : 2153.0,
    "pct1ResTime" : 921.0,
    "pct2ResTime" : 1188.0,
    "pct3ResTime" : 2090.2999999999975,
    "throughput" : 0.4954849414828443,
    "receivedKBytesPerSec" : 0.25500055093892476,
    "sentKBytesPerSec" : 0.2530650628862574
  },
  "News/sites/default/files/styles/frontpage__featured_news/public/images/202411/mit-josephine-carstensen-david-mcgee.png-313" : {
    "transaction" : "News/sites/default/files/styles/frontpage__featured_news/public/images/202411/mit-josephine-carstensen-david-mcgee.png-313",
    "sampleCount" : 80,
    "errorCount" : 72,
    "errorPct" : 90.0,
    "meanResTime" : 10636.974999999999,
    "medianResTime" : 9842.0,
    "minResTime" : 704.0,
    "maxResTime" : 31141.0,
    "pct1ResTime" : 17857.7,
    "pct2ResTime" : 21133.05,
    "pct3ResTime" : 31141.0,
    "throughput" : 0.13425206496457423,
    "receivedKBytesPerSec" : 20.860730565650098,
    "sentKBytesPerSec" : 0.09216718913095281
  },
  "News/sites/default/files/styles/frontpage__featured_news/public/images/202411/mit-whitehead-proteolethargy.png-318" : {
    "transaction" : "News/sites/default/files/styles/frontpage__featured_news/public/images/202411/mit-whitehead-proteolethargy.png-318",
    "sampleCount" : 80,
    "errorCount" : 74,
    "errorPct" : 92.5,
    "meanResTime" : 13615.112500000001,
    "medianResTime" : 13252.0,
    "minResTime" : 639.0,
    "maxResTime" : 53229.0,
    "pct1ResTime" : 19681.800000000003,
    "pct2ResTime" : 25400.1,
    "pct3ResTime" : 53229.0,
    "throughput" : 0.14909406717433196,
    "receivedKBytesPerSec" : 28.99428611547522,
    "sentKBytesPerSec" : 0.10119177410757883
  },
  "MIT/themes/mit/assets/js/CombinedSearch.68627c63c12e4144b6e6.js-75" : {
    "transaction" : "MIT/themes/mit/assets/js/CombinedSearch.68627c63c12e4144b6e6.js-75",
    "sampleCount" : 128,
    "errorCount" : 71,
    "errorPct" : 55.46875,
    "meanResTime" : 26344.21875,
    "medianResTime" : 585.5,
    "minResTime" : 50.0,
    "maxResTime" : 3108778.0,
    "pct1ResTime" : 2915.9,
    "pct2ResTime" : 11951.649999999987,
    "pct3ResTime" : 2228900.019999981,
    "throughput" : 0.0405918288648495,
    "receivedKBytesPerSec" : 0.48646181492171486,
    "sentKBytesPerSec" : 0.023480467778808783
  },
  "MIT/themes/mit/assets/css/main.css-62" : {
    "transaction" : "MIT/themes/mit/assets/css/main.css-62",
    "sampleCount" : 129,
    "errorCount" : 112,
    "errorPct" : 86.82171,
    "meanResTime" : 2226.891472868216,
    "medianResTime" : 845.0,
    "minResTime" : 124.0,
    "maxResTime" : 73311.0,
    "pct1ResTime" : 2750.0,
    "pct2ResTime" : 6914.5,
    "pct3ResTime" : 61772.69999999956,
    "throughput" : 0.45258393853278606,
    "receivedKBytesPerSec" : 32.11136081070414,
    "sentKBytesPerSec" : 0.26032415995684666
  },
  "News/sites/default/files/styles/frontpage__featured_news/public/images/202412/MIT-EnergySystem-01.jpg-324" : {
    "transaction" : "News/sites/default/files/styles/frontpage__featured_news/public/images/202412/MIT-EnergySystem-01.jpg-324",
    "sampleCount" : 80,
    "errorCount" : 56,
    "errorPct" : 70.0,
    "meanResTime" : 6872.887500000001,
    "medianResTime" : 6164.5,
    "minResTime" : 134.0,
    "maxResTime" : 21049.0,
    "pct1ResTime" : 12221.300000000001,
    "pct2ResTime" : 15016.85,
    "pct3ResTime" : 21049.0,
    "throughput" : 0.15534342547787522,
    "receivedKBytesPerSec" : 16.287519229817004,
    "sentKBytesPerSec" : 0.10276710937924766
  },
  "News/vi/QtIxTFyn_ZQ/maxresdefault.jpg-327" : {
    "transaction" : "News/vi/QtIxTFyn_ZQ/maxresdefault.jpg-327",
    "sampleCount" : 80,
    "errorCount" : 2,
    "errorPct" : 2.5,
    "meanResTime" : 1245.5249999999999,
    "medianResTime" : 981.5,
    "minResTime" : 113.0,
    "maxResTime" : 5485.0,
    "pct1ResTime" : 2559.500000000001,
    "pct2ResTime" : 3501.1000000000004,
    "pct3ResTime" : 5485.0,
    "throughput" : 0.15615972016178148,
    "receivedKBytesPerSec" : 28.033708326094676,
    "sentKBytesPerSec" : 0.10735980761122475
  },
  "MIT/q/climate%20c?count=3-51" : {
    "transaction" : "MIT/q/climate%20c?count=3-51",
    "sampleCount" : 129,
    "errorCount" : 30,
    "errorPct" : 23.255814,
    "meanResTime" : 565.8527131782946,
    "medianResTime" : 83.0,
    "minResTime" : 42.0,
    "maxResTime" : 9702.0,
    "pct1ResTime" : 1235.0,
    "pct2ResTime" : 2470.0,
    "pct3ResTime" : 8969.999999999973,
    "throughput" : 0.6986000920635781,
    "receivedKBytesPerSec" : 0.3602156724702824,
    "sentKBytesPerSec" : 0.3540756325986299
  },
  "Research/research/centers-labs-programs/-227" : {
    "transaction" : "Research/research/centers-labs-programs/-227",
    "sampleCount" : 80,
    "errorCount" : 8,
    "errorPct" : 10.0,
    "meanResTime" : 1773.4499999999998,
    "medianResTime" : 427.0,
    "minResTime" : 76.0,
    "maxResTime" : 74620.0,
    "pct1ResTime" : 1449.8000000000006,
    "pct2ResTime" : 2616.2000000000007,
    "pct3ResTime" : 74620.0,
    "throughput" : 0.09883217432018906,
    "receivedKBytesPerSec" : 1.143422626143828,
    "sentKBytesPerSec" : 0.07132517267833957
  },
  "MIT/search/-48" : {
    "transaction" : "MIT/search/-48",
    "sampleCount" : 130,
    "errorCount" : 68,
    "errorPct" : 52.307693,
    "meanResTime" : 24774.67692307692,
    "medianResTime" : 481.5,
    "minResTime" : 53.0,
    "maxResTime" : 2830390.0,
    "pct1ResTime" : 4715.400000000001,
    "pct2ResTime" : 18665.499999999996,
    "pct3ResTime" : 1976648.1399999938,
    "throughput" : 0.041209348562617924,
    "receivedKBytesPerSec" : 0.3801525257051237,
    "sentKBytesPerSec" : 0.028872237923600406
  },
  "MIT/q/climate%20ch?count=3-52" : {
    "transaction" : "MIT/q/climate%20ch?count=3-52",
    "sampleCount" : 129,
    "errorCount" : 26,
    "errorPct" : 20.155039,
    "meanResTime" : 339.1085271317831,
    "medianResTime" : 79.0,
    "minResTime" : 44.0,
    "maxResTime" : 4541.0,
    "pct1ResTime" : 802.0,
    "pct2ResTime" : 1465.5,
    "pct3ResTime" : 4403.599999999995,
    "throughput" : 0.49311738104976666,
    "receivedKBytesPerSec" : 0.25426364960378595,
    "sentKBytesPerSec" : 0.2504111700643346
  },
  "News/sites/default/files/styles/frontpage__featured_news/public/images/202412/MIT-LLMExplanations-01-press.jpg-320" : {
    "transaction" : "News/sites/default/files/styles/frontpage__featured_news/public/images/202412/MIT-LLMExplanations-01-press.jpg-320",
    "sampleCount" : 80,
    "errorCount" : 69,
    "errorPct" : 86.25,
    "meanResTime" : 12517.074999999999,
    "medianResTime" : 12369.0,
    "minResTime" : 220.0,
    "maxResTime" : 57000.0,
    "pct1ResTime" : 22783.5,
    "pct2ResTime" : 25767.900000000005,
    "pct3ResTime" : 57000.0,
    "throughput" : 0.15549106995348871,
    "receivedKBytesPerSec" : 28.953708941854114,
    "sentKBytesPerSec" : 0.10553348986101041
  },
  "Research/files/images/201806/11_preview_0.jpeg-220" : {
    "transaction" : "Research/files/images/201806/11_preview_0.jpeg-220",
    "sampleCount" : 80,
    "errorCount" : 42,
    "errorPct" : 52.5,
    "meanResTime" : 2318.0375,
    "medianResTime" : 1501.0,
    "minResTime" : 298.0,
    "maxResTime" : 19048.0,
    "pct1ResTime" : 5039.700000000001,
    "pct2ResTime" : 6891.6500000000015,
    "pct3ResTime" : 19048.0,
    "throughput" : 0.09822652017818291,
    "receivedKBytesPerSec" : 17.69401119045631,
    "sentKBytesPerSec" : 0.059473088389134184
  },
  "MIT/q/clim?count=3-42" : {
    "transaction" : "MIT/q/clim?count=3-42",
    "sampleCount" : 130,
    "errorCount" : 26,
    "errorPct" : 20.0,
    "meanResTime" : 695.0384615384615,
    "medianResTime" : 80.0,
    "minResTime" : 44.0,
    "maxResTime" : 49921.0,
    "pct1ResTime" : 870.200000000001,
    "pct2ResTime" : 1233.5,
    "pct3ResTime" : 35659.449999999895,
    "throughput" : 0.40246307401295933,
    "receivedKBytesPerSec" : 0.20752002253793214,
    "sentKBytesPerSec" : 0.20123153700647964
  },
  "News/sites/default/files/styles/frontpage__featured_news/public/images/202411/cop16-Coalition-of-Cities.jpg-312" : {
    "transaction" : "News/sites/default/files/styles/frontpage__featured_news/public/images/202411/cop16-Coalition-of-Cities.jpg-312",
    "sampleCount" : 80,
    "errorCount" : 36,
    "errorPct" : 45.0,
    "meanResTime" : 5209.424999999999,
    "medianResTime" : 3901.5,
    "minResTime" : 400.0,
    "maxResTime" : 39794.0,
    "pct1ResTime" : 8935.600000000002,
    "pct2ResTime" : 12498.450000000003,
    "pct3ResTime" : 39794.0,
    "throughput" : 0.12997457372401525,
    "receivedKBytesPerSec" : 9.306011298649077,
    "sentKBytesPerSec" : 0.08783437989943217
  },
  "News/vi/X8bMIocY0IM/maxresdefault.jpg-328" : {
    "transaction" : "News/vi/X8bMIocY0IM/maxresdefault.jpg-328",
    "sampleCount" : 80,
    "errorCount" : 0,
    "errorPct" : 0.0,
    "meanResTime" : 606.4,
    "medianResTime" : 424.0,
    "minResTime" : 124.0,
    "maxResTime" : 2510.0,
    "pct1ResTime" : 1262.1000000000001,
    "pct2ResTime" : 1472.8000000000002,
    "pct3ResTime" : 2510.0,
    "throughput" : 0.1559612280387096,
    "receivedKBytesPerSec" : 16.945857572307524,
    "sentKBytesPerSec" : 0.10722334427661284
  },
  "MIT/q/climate%20change?count=3-65" : {
    "transaction" : "MIT/q/climate%20change?count=3-65",
    "sampleCount" : 128,
    "errorCount" : 25,
    "errorPct" : 19.53125,
    "meanResTime" : 405.3203125,
    "medianResTime" : 79.0,
    "minResTime" : 44.0,
    "maxResTime" : 15925.0,
    "pct1ResTime" : 692.7000000000003,
    "pct2ResTime" : 1120.6999999999991,
    "pct3ResTime" : 12654.95999999993,
    "throughput" : 0.4382015932736055,
    "receivedKBytesPerSec" : 0.22594769653170285,
    "sentKBytesPerSec" : 0.22423597155797784
  },
  "News/sites/default/files/styles/frontpage__featured_news/public/images/202412/Daniela-Rus-JSA.jpg-310" : {
    "transaction" : "News/sites/default/files/styles/frontpage__featured_news/public/images/202412/Daniela-Rus-JSA.jpg-310",
    "sampleCount" : 80,
    "errorCount" : 49,
    "errorPct" : 61.25,
    "meanResTime" : 6939.774999999998,
    "medianResTime" : 5987.0,
    "minResTime" : 966.0,
    "maxResTime" : 94911.0,
    "pct1ResTime" : 9136.800000000001,
    "pct2ResTime" : 10078.85,
    "pct3ResTime" : 94911.0,
    "throughput" : 0.12176671324243449,
    "receivedKBytesPerSec" : 8.582189891574352,
    "sentKBytesPerSec" : 0.08109853362435578
  },
  "News/sites/default/files/styles/frontpage__featured_news/public/images/202411/mit-spi-exvd-2024-a1.jpg-346" : {
    "transaction" : "News/sites/default/files/styles/frontpage__featured_news/public/images/202411/mit-spi-exvd-2024-a1.jpg-346",
    "sampleCount" : 80,
    "errorCount" : 39,
    "errorPct" : 48.75,
    "meanResTime" : 5397.937500000001,
    "medianResTime" : 4389.5,
    "minResTime" : 249.0,
    "maxResTime" : 21583.0,
    "pct1ResTime" : 12356.50000000001,
    "pct2ResTime" : 14796.750000000002,
    "pct3ResTime" : 21583.0,
    "throughput" : 0.2884504442136841,
    "receivedKBytesPerSec" : 42.103662751627944,
    "sentKBytesPerSec" : 0.19352095231914157
  },
  "MIT/-1" : {
    "transaction" : "MIT/-1",
    "sampleCount" : 150,
    "errorCount" : 136,
    "errorPct" : 90.666664,
    "meanResTime" : 293260.95333333337,
    "medianResTime" : 3263.0,
    "minResTime" : 180.0,
    "maxResTime" : 3142042.0,
    "pct1ResTime" : 41057.10000000008,
    "pct2ResTime" : 3080149.3,
    "pct3ResTime" : 3135874.06,
    "throughput" : 0.04752776413554918,
    "receivedKBytesPerSec" : 0.5336591254297302,
    "sentKBytesPerSec" : 0.029693713264998967
  },
  "MIT/q/climate%20change?count=3-67" : {
    "transaction" : "MIT/q/climate%20change?count=3-67",
    "sampleCount" : 128,
    "errorCount" : 27,
    "errorPct" : 21.09375,
    "meanResTime" : 391.97656249999983,
    "medianResTime" : 81.5,
    "minResTime" : 42.0,
    "maxResTime" : 9923.0,
    "pct1ResTime" : 990.4000000000001,
    "pct2ResTime" : 1759.9999999999977,
    "pct3ResTime" : 8024.079999999959,
    "throughput" : 0.43825860681697565,
    "receivedKBytesPerSec" : 0.22597709414000308,
    "sentKBytesPerSec" : 0.22426514645712428
  },
  "News/sites/default/files/styles/frontpage__featured_news/public/images/202411/single-truthful-reward.png-321" : {
    "transaction" : "News/sites/default/files/styles/frontpage__featured_news/public/images/202411/single-truthful-reward.png-321",
    "sampleCount" : 80,
    "errorCount" : 3,
    "errorPct" : 3.75,
    "meanResTime" : 2038.1874999999986,
    "medianResTime" : 1480.5,
    "minResTime" : 101.0,
    "maxResTime" : 21308.0,
    "pct1ResTime" : 3499.7000000000003,
    "pct2ResTime" : 4532.150000000001,
    "pct3ResTime" : 21308.0,
    "throughput" : 0.15567533908034792,
    "receivedKBytesPerSec" : 4.287310620341902,
    "sentKBytesPerSec" : 0.10474639514292942
  },
  "News/api/recent-news/a345c78b-8992-469a-bc15-0d798952fa64-329" : {
    "transaction" : "News/api/recent-news/a345c78b-8992-469a-bc15-0d798952fa64-329",
    "sampleCount" : 80,
    "errorCount" : 0,
    "errorPct" : 0.0,
    "meanResTime" : 398.2750000000001,
    "medianResTime" : 218.5,
    "minResTime" : 61.0,
    "maxResTime" : 2679.0,
    "pct1ResTime" : 839.2000000000005,
    "pct2ResTime" : 1373.1500000000003,
    "pct3ResTime" : 2679.0,
    "throughput" : 0.15688397057641132,
    "receivedKBytesPerSec" : 0.43749983147229726,
    "sentKBytesPerSec" : 0.10096341465806158
  },
  "News/sites/default/files/styles/frontpage__featured_news/public/images/202411/MIT-Catherine_DIgnazio-01-press.jpg-344" : {
    "transaction" : "News/sites/default/files/styles/frontpage__featured_news/public/images/202411/MIT-Catherine_DIgnazio-01-press.jpg-344",
    "sampleCount" : 80,
    "errorCount" : 26,
    "errorPct" : 32.5,
    "meanResTime" : 4055.2874999999985,
    "medianResTime" : 3973.5,
    "minResTime" : 145.0,
    "maxResTime" : 16266.0,
    "pct1ResTime" : 7457.700000000005,
    "pct2ResTime" : 8576.1,
    "pct3ResTime" : 16266.0,
    "throughput" : 0.2533473518868044,
    "receivedKBytesPerSec" : 22.98435708755051,
    "sentKBytesPerSec" : 0.1726918472822163
  },
  "News/sites/default/files/styles/frontpage__featured_news/public/images/202412/MIT-Uprooted-A1.jpg-341" : {
    "transaction" : "News/sites/default/files/styles/frontpage__featured_news/public/images/202412/MIT-Uprooted-A1.jpg-341",
    "sampleCount" : 80,
    "errorCount" : 35,
    "errorPct" : 43.75,
    "meanResTime" : 4462.500000000001,
    "medianResTime" : 4396.0,
    "minResTime" : 158.0,
    "maxResTime" : 14773.0,
    "pct1ResTime" : 8263.5,
    "pct2ResTime" : 10141.95,
    "pct3ResTime" : 14773.0,
    "throughput" : 0.2619481080797894,
    "receivedKBytesPerSec" : 27.72610086762125,
    "sentKBytesPerSec" : 0.17446153292032848
  },
  "News/sites/default/files/styles/frontpage__featured_news/public/images/202412/Construction-waste.jpg-307" : {
    "transaction" : "News/sites/default/files/styles/frontpage__featured_news/public/images/202412/Construction-waste.jpg-307",
    "sampleCount" : 80,
    "errorCount" : 67,
    "errorPct" : 83.75,
    "meanResTime" : 9175.7,
    "medianResTime" : 8339.5,
    "minResTime" : 1296.0,
    "maxResTime" : 32986.0,
    "pct1ResTime" : 15565.300000000001,
    "pct2ResTime" : 20344.150000000012,
    "pct3ResTime" : 32986.0,
    "throughput" : 0.11709516177428445,
    "receivedKBytesPerSec" : 12.223418426295913,
    "sentKBytesPerSec" : 0.07833025958533675
  },
  "News/sites/default/files/styles/frontpage__featured_news/public/images/202412/MIT-Gastric-Balloon-01-press.jpg-342" : {
    "transaction" : "News/sites/default/files/styles/frontpage__featured_news/public/images/202412/MIT-Gastric-Balloon-01-press.jpg-342",
    "sampleCount" : 80,
    "errorCount" : 14,
    "errorPct" : 17.5,
    "meanResTime" : 2996.3874999999994,
    "medianResTime" : 2606.0,
    "minResTime" : 109.0,
    "maxResTime" : 16758.0,
    "pct1ResTime" : 5884.200000000001,
    "pct2ResTime" : 8042.000000000004,
    "pct3ResTime" : 16758.0,
    "throughput" : 0.2479513023642157,
    "receivedKBytesPerSec" : 14.061075611781096,
    "sentKBytesPerSec" : 0.16828726088196277
  },
  "News/sites/default/files/styles/frontpage__featured_news/public/images/202412/MIT-Score-Distillation-01-press.jpg-339" : {
    "transaction" : "News/sites/default/files/styles/frontpage__featured_news/public/images/202412/MIT-Score-Distillation-01-press.jpg-339",
    "sampleCount" : 80,
    "errorCount" : 45,
    "errorPct" : 56.25,
    "meanResTime" : 5597.849999999999,
    "medianResTime" : 5191.0,
    "minResTime" : 258.0,
    "maxResTime" : 31564.0,
    "pct1ResTime" : 9934.2,
    "pct2ResTime" : 10808.150000000001,
    "pct3ResTime" : 31564.0,
    "throughput" : 0.267730448983963,
    "receivedKBytesPerSec" : 33.63364418999826,
    "sentKBytesPerSec" : 0.1824959505769591
  },
  "News/-301" : {
    "transaction" : "News/-301",
    "sampleCount" : 80,
    "errorCount" : 27,
    "errorPct" : 33.75,
    "meanResTime" : 5244.8875,
    "medianResTime" : 2438.5,
    "minResTime" : 408.0,
    "maxResTime" : 25746.0,
    "pct1ResTime" : 16105.000000000002,
    "pct2ResTime" : 18822.4,
    "pct3ResTime" : 25746.0,
    "throughput" : 0.10036885554412465,
    "receivedKBytesPerSec" : 3.69148980903257,
    "sentKBytesPerSec" : 0.06707633953215568
  },
  "MIT/campus-map/objimgs/object-54.jpg-127" : {
    "transaction" : "MIT/campus-map/objimgs/object-54.jpg-127",
    "sampleCount" : 124,
    "errorCount" : 121,
    "errorPct" : 97.58064,
    "meanResTime" : 279775.1048387097,
    "medianResTime" : 4545.5,
    "minResTime" : 194.0,
    "maxResTime" : 3092220.0,
    "pct1ResTime" : 174582.5,
    "pct2ResTime" : 3066235.75,
    "pct3ResTime" : 3091724.25,
    "throughput" : 0.039346854901174344,
    "receivedKBytesPerSec" : 0.3883363774921394,
    "sentKBytesPerSec" : 0.020588182330787106
  },
  "MIT/q/cli?count=3-41" : {
    "transaction" : "MIT/q/cli?count=3-41",
    "sampleCount" : 132,
    "errorCount" : 107,
    "errorPct" : 81.06061,
    "meanResTime" : 49605.84848484849,
    "medianResTime" : 1390.0,
    "minResTime" : 141.0,
    "maxResTime" : 3144320.0,
    "pct1ResTime" : 5670.700000000001,
    "pct2ResTime" : 12847.599999999995,
    "pct3ResTime" : 3117304.219999999,
    "throughput" : 0.04183771530575763,
    "receivedKBytesPerSec" : 0.02336471485536829,
    "sentKBytesPerSec" : 0.020561667167979695
  },
  "Research/files/images/201805/research-2_0.mp4-197" : {
    "transaction" : "Research/files/images/201805/research-2_0.mp4-197",
    "sampleCount" : 95,
    "errorCount" : 95,
    "errorPct" : 100.0,
    "meanResTime" : 452290.16842105263,
    "medianResTime" : 268020.0,
    "minResTime" : 10270.0,
    "maxResTime" : 3120516.0,
    "pct1ResTime" : 630390.8,
    "pct2ResTime" : 3057301.6,
    "pct3ResTime" : 3120516.0,
    "throughput" : 0.030176452837380685,
    "receivedKBytesPerSec" : 114.74069592459063,
    "sentKBytesPerSec" : 0.015764156627701982
  },
  "News/sites/default/files/styles/frontpage__featured_news/public/images/202411/dopamine.jpg-319" : {
    "transaction" : "News/sites/default/files/styles/frontpage__featured_news/public/images/202411/dopamine.jpg-319",
    "sampleCount" : 80,
    "errorCount" : 47,
    "errorPct" : 58.75,
    "meanResTime" : 6120.55,
    "medianResTime" : 5476.0,
    "minResTime" : 400.0,
    "maxResTime" : 28221.0,
    "pct1ResTime" : 11292.000000000005,
    "pct2ResTime" : 14859.35,
    "pct3ResTime" : 28221.0,
    "throughput" : 0.14570595445596127,
    "receivedKBytesPerSec" : 12.278295014943966,
    "sentKBytesPerSec" : 0.09604640552516978
  },
  "MIT/q/climat?count=3-44" : {
    "transaction" : "MIT/q/climat?count=3-44",
    "sampleCount" : 130,
    "errorCount" : 30,
    "errorPct" : 23.076923,
    "meanResTime" : 499.1692307692308,
    "medianResTime" : 79.0,
    "minResTime" : 43.0,
    "maxResTime" : 18673.0,
    "pct1ResTime" : 849.4000000000001,
    "pct2ResTime" : 1632.8999999999996,
    "pct3ResTime" : 14348.189999999968,
    "throughput" : 0.7298163669741252,
    "receivedKBytesPerSec" : 0.3763115642210333,
    "sentKBytesPerSec" : 0.36633360607880894
  },
  "News/sites/default/files/styles/frontpage__featured_news/public/images/202412/MIT_AI-Economy-01-PRESS.jpg-331" : {
    "transaction" : "News/sites/default/files/styles/frontpage__featured_news/public/images/202412/MIT_AI-Economy-01-PRESS.jpg-331",
    "sampleCount" : 80,
    "errorCount" : 46,
    "errorPct" : 57.5,
    "meanResTime" : 5786.500000000001,
    "medianResTime" : 5374.0,
    "minResTime" : 197.0,
    "maxResTime" : 22280.0,
    "pct1ResTime" : 9992.1,
    "pct2ResTime" : 13266.500000000007,
    "pct3ResTime" : 22280.0,
    "throughput" : 0.1574672960109597,
    "receivedKBytesPerSec" : 14.197593176966668,
    "sentKBytesPerSec" : 0.10610589281988497
  },
  "News/sites/default/files/styles/frontpage__featured_news/public/images/202411/MIT-Gio-Traverso_press.jpg-345" : {
    "transaction" : "News/sites/default/files/styles/frontpage__featured_news/public/images/202411/MIT-Gio-Traverso_press.jpg-345",
    "sampleCount" : 80,
    "errorCount" : 10,
    "errorPct" : 12.5,
    "meanResTime" : 2667.6,
    "medianResTime" : 2215.5,
    "minResTime" : 121.0,
    "maxResTime" : 16810.0,
    "pct1ResTime" : 5008.5,
    "pct2ResTime" : 6648.400000000001,
    "pct3ResTime" : 16810.0,
    "throughput" : 0.2815711671124877,
    "receivedKBytesPerSec" : 21.27707372765029,
    "sentKBytesPerSec" : 0.18945559974658593
  },
  "News/vi/1yihsaPWrnk/maxresdefault.jpg-326" : {
    "transaction" : "News/vi/1yihsaPWrnk/maxresdefault.jpg-326",
    "sampleCount" : 80,
    "errorCount" : 1,
    "errorPct" : 1.25,
    "meanResTime" : 1437.2375000000004,
    "medianResTime" : 1106.0,
    "minResTime" : 284.0,
    "maxResTime" : 11101.0,
    "pct1ResTime" : 2475.1000000000004,
    "pct2ResTime" : 3367.1500000000005,
    "pct3ResTime" : 11101.0,
    "throughput" : 0.15525931216243227,
    "receivedKBytesPerSec" : 14.904249580799856,
    "sentKBytesPerSec" : 0.10540651739777629
  },
  "News/api/recent-news/a345c78b-8992-469a-bc15-0d798952fa64-338" : {
    "transaction" : "News/api/recent-news/a345c78b-8992-469a-bc15-0d798952fa64-338",
    "sampleCount" : 80,
    "errorCount" : 2,
    "errorPct" : 2.5,
    "meanResTime" : 811.1,
    "medianResTime" : 224.0,
    "minResTime" : 54.0,
    "maxResTime" : 16673.0,
    "pct1ResTime" : 1452.1000000000001,
    "pct2ResTime" : 1799.9500000000003,
    "pct3ResTime" : 16673.0,
    "throughput" : 0.24720198255990014,
    "receivedKBytesPerSec" : 0.6877296757482495,
    "sentKBytesPerSec" : 0.15908799463571696
  },
  "News/sites/default/files/styles/frontpage__featured_news/public/images/202412/mit-music-W18-00_0.jpg-332" : {
    "transaction" : "News/sites/default/files/styles/frontpage__featured_news/public/images/202412/mit-music-W18-00_0.jpg-332",
    "sampleCount" : 80,
    "errorCount" : 59,
    "errorPct" : 73.75,
    "meanResTime" : 8852.325,
    "medianResTime" : 7613.0,
    "minResTime" : 271.0,
    "maxResTime" : 91221.0,
    "pct1ResTime" : 14463.0,
    "pct2ResTime" : 16042.800000000001,
    "pct3ResTime" : 91221.0,
    "throughput" : 0.20555459915568447,
    "receivedKBytesPerSec" : 33.27295635369266,
    "sentKBytesPerSec" : 0.1375047855680116
  },
  "Research/themes/mit/assets/img/cursors/pause.svg-194" : {
    "transaction" : "Research/themes/mit/assets/img/cursors/pause.svg-194",
    "sampleCount" : 99,
    "errorCount" : 10,
    "errorPct" : 10.10101,
    "meanResTime" : 31714.58585858586,
    "medianResTime" : 84.0,
    "minResTime" : 55.0,
    "maxResTime" : 3080004.0,
    "pct1ResTime" : 1417.0,
    "pct2ResTime" : 1878.0,
    "pct3ResTime" : 3080004.0,
    "throughput" : 0.03142672573198082,
    "receivedKBytesPerSec" : 0.024210817678168108,
    "sentKBytesPerSec" : 0.019747104138328385
  },
  "Research/themes/mit/assets/css/main.css-186" : {
    "transaction" : "Research/themes/mit/assets/css/main.css-186",
    "sampleCount" : 103,
    "errorCount" : 43,
    "errorPct" : 41.747574,
    "meanResTime" : 61548.834951456316,
    "medianResTime" : 1025.0,
    "minResTime" : 73.0,
    "maxResTime" : 3143814.0,
    "pct1ResTime" : 6841.6,
    "pct2ResTime" : 10789.199999999997,
    "pct3ResTime" : 3136591.519999999,
    "throughput" : 0.03268833638900517,
    "receivedKBytesPerSec" : 2.276299189797367,
    "sentKBytesPerSec" : 0.017967551708663775
  },
  "MIT/themes/mit/assets/js/modernizr.js-63" : {
    "transaction" : "MIT/themes/mit/assets/js/modernizr.js-63",
    "sampleCount" : 129,
    "errorCount" : 71,
    "errorPct" : 55.03876,
    "meanResTime" : 2536.4496124031007,
    "medianResTime" : 525.0,
    "minResTime" : 51.0,
    "maxResTime" : 41024.0,
    "pct1ResTime" : 2854.0,
    "pct2ResTime" : 20222.5,
    "pct3ResTime" : 39839.89999999996,
    "throughput" : 0.45536536893419793,
    "receivedKBytesPerSec" : 2.733526291834487,
    "sentKBytesPerSec" : 0.25703240551168594
  },
  "Research/files/images/201807/MIT-Sole-Vibes_0.jpg-187" : {
    "transaction" : "Research/files/images/201807/MIT-Sole-Vibes_0.jpg-187",
    "sampleCount" : 101,
    "errorCount" : 70,
    "errorPct" : 69.30693,
    "meanResTime" : 65469.87128712871,
    "medianResTime" : 2097.0,
    "minResTime" : 223.0,
    "maxResTime" : 3079239.0,
    "pct1ResTime" : 13539.999999999982,
    "pct2ResTime" : 37439.0,
    "pct3ResTime" : 3078690.72,
    "throughput" : 0.03205481182397275,
    "receivedKBytesPerSec" : 5.249977149045036,
    "sentKBytesPerSec" : 0.019115917280971215
  },
  "Research/themes/mit/assets/img/cursors/plus.svg-195" : {
    "transaction" : "Research/themes/mit/assets/img/cursors/plus.svg-195",
    "sampleCount" : 98,
    "errorCount" : 8,
    "errorPct" : 8.163265,
    "meanResTime" : 1138.275510204082,
    "medianResTime" : 87.0,
    "minResTime" : 45.0,
    "maxResTime" : 56322.0,
    "pct1ResTime" : 1234.4,
    "pct2ResTime" : 2879.4999999999927,
    "pct3ResTime" : 56322.0,
    "throughput" : 0.21502356482741067,
    "receivedKBytesPerSec" : 0.15748796252007619,
    "sentKBytesPerSec" : 0.13627958356737258
  },
  "Research/themes/mit/assets/js/Slider.078a4f7ab331b45e9a4e.js-205" : {
    "transaction" : "Research/themes/mit/assets/js/Slider.078a4f7ab331b45e9a4e.js-205",
    "sampleCount" : 96,
    "errorCount" : 36,
    "errorPct" : 37.5,
    "meanResTime" : 32552.0,
    "medianResTime" : 1247.0,
    "minResTime" : 93.0,
    "maxResTime" : 2922616.0,
    "pct1ResTime" : 4986.499999999999,
    "pct2ResTime" : 9922.699999999993,
    "pct3ResTime" : 2922616.0,
    "throughput" : 0.030488792510428117,
    "receivedKBytesPerSec" : 1.3323106710495893,
    "sentKBytesPerSec" : 0.01691237239169968
  },
  "News/sites/default/files/styles/frontpage__featured_news/public/images/202412/MIT_Biodegradable-Microplastics-01-press.jpg-325" : {
    "transaction" : "News/sites/default/files/styles/frontpage__featured_news/public/images/202412/MIT_Biodegradable-Microplastics-01-press.jpg-325",
    "sampleCount" : 80,
    "errorCount" : 47,
    "errorPct" : 58.75,
    "meanResTime" : 5586.262499999999,
    "medianResTime" : 5055.0,
    "minResTime" : 123.0,
    "maxResTime" : 17662.0,
    "pct1ResTime" : 9131.900000000001,
    "pct2ResTime" : 12779.100000000006,
    "pct3ResTime" : 17662.0,
    "throughput" : 0.15530783955147096,
    "receivedKBytesPerSec" : 13.542272958745384,
    "sentKBytesPerSec" : 0.10722914312782224
  },
  "MIT/themes/mit/assets/js/main.js-64" : {
    "transaction" : "MIT/themes/mit/assets/js/main.js-64",
    "sampleCount" : 129,
    "errorCount" : 125,
    "errorPct" : 96.89922,
    "meanResTime" : 28069.565891472866,
    "medianResTime" : 2749.0,
    "minResTime" : 196.0,
    "maxResTime" : 3008301.0,
    "pct1ResTime" : 11489.0,
    "pct2ResTime" : 19515.5,
    "pct3ResTime" : 2124105.8999999664,
    "throughput" : 0.04090017155878163,
    "receivedKBytesPerSec" : 14.848940175295281,
    "sentKBytesPerSec" : 0.02270910688292817
  },
  "News/sites/default/files/styles/frontpage__featured_news/public/images/202411/MlenToo-Wesley.jpg-340" : {
    "transaction" : "News/sites/default/files/styles/frontpage__featured_news/public/images/202411/MlenToo-Wesley.jpg-340",
    "sampleCount" : 80,
    "errorCount" : 2,
    "errorPct" : 2.5,
    "meanResTime" : 1982.6250000000005,
    "medianResTime" : 1670.0,
    "minResTime" : 86.0,
    "maxResTime" : 15712.0,
    "pct1ResTime" : 3882.6000000000004,
    "pct2ResTime" : 4536.2,
    "pct3ResTime" : 15712.0,
    "throughput" : 0.2586159520784641,
    "receivedKBytesPerSec" : 11.161920685114065,
    "sentKBytesPerSec" : 0.1719897103178067
  },
  "News/sites/default/files/styles/frontpage__featured_news/public/images/202412/MIT-data-debias-01.jpg-305" : {
    "transaction" : "News/sites/default/files/styles/frontpage__featured_news/public/images/202412/MIT-data-debias-01.jpg-305",
    "sampleCount" : 80,
    "errorCount" : 71,
    "errorPct" : 88.75,
    "meanResTime" : 16292.362500000007,
    "medianResTime" : 13563.5,
    "minResTime" : 823.0,
    "maxResTime" : 100808.0,
    "pct1ResTime" : 27907.400000000016,
    "pct2ResTime" : 42427.70000000001,
    "pct3ResTime" : 100808.0,
    "throughput" : 0.10323379874570936,
    "receivedKBytesPerSec" : 17.213034991015434,
    "sentKBytesPerSec" : 0.06905776576251065
  },
  "MIT/q/climate%20?count=3-50" : {
    "transaction" : "MIT/q/climate%20?count=3-50",
    "sampleCount" : 129,
    "errorCount" : 20,
    "errorPct" : 15.503876,
    "meanResTime" : 928.6124031007752,
    "medianResTime" : 81.0,
    "minResTime" : 43.0,
    "maxResTime" : 75996.0,
    "pct1ResTime" : 667.0,
    "pct2ResTime" : 1119.0,
    "pct3ResTime" : 56252.39999999925,
    "throughput" : 0.45531554426090637,
    "receivedKBytesPerSec" : 0.23477207750952986,
    "sentKBytesPerSec" : 0.23032563664760694
  },
  "News/sites/default/files/styles/frontpage__featured_news/public/images/202412/hale-bradt-mit-00_0.jpg-309" : {
    "transaction" : "News/sites/default/files/styles/frontpage__featured_news/public/images/202412/hale-bradt-mit-00_0.jpg-309",
    "sampleCount" : 80,
    "errorCount" : 76,
    "errorPct" : 95.0,
    "meanResTime" : 17092.125000000004,
    "medianResTime" : 13805.0,
    "minResTime" : 1308.0,
    "maxResTime" : 104343.0,
    "pct1ResTime" : 22698.9,
    "pct2ResTime" : 52133.60000000004,
    "pct3ResTime" : 104343.0,
    "throughput" : 0.12396239600717124,
    "receivedKBytesPerSec" : 21.637993341282424,
    "sentKBytesPerSec" : 0.08304512076261666
  },
  "News/sites/default/files/styles/frontpage__featured_news/public/images/202412/mit-womens-cross-country-champions.jpg-311" : {
    "transaction" : "News/sites/default/files/styles/frontpage__featured_news/public/images/202412/mit-womens-cross-country-champions.jpg-311",
    "sampleCount" : 80,
    "errorCount" : 45,
    "errorPct" : 56.25,
    "meanResTime" : 7445.300000000005,
    "medianResTime" : 5428.5,
    "minResTime" : 655.0,
    "maxResTime" : 82630.0,
    "pct1ResTime" : 16520.000000000036,
    "pct2ResTime" : 20939.100000000006,
    "pct3ResTime" : 82630.0,
    "throughput" : 0.1280047105733491,
    "receivedKBytesPerSec" : 10.130616556689287,
    "sentKBytesPerSec" : 0.08653287190968628
  },
  "MIT/q/climate%20change-84" : {
    "transaction" : "MIT/q/climate%20change-84",
    "sampleCount" : 127,
    "errorCount" : 127,
    "errorPct" : 100.0,
    "meanResTime" : 88450.66141732284,
    "medianResTime" : 11744.0,
    "minResTime" : 1660.0,
    "maxResTime" : 3117761.0,
    "pct1ResTime" : 33562.000000000015,
    "pct2ResTime" : 68349.8,
    "pct3ResTime" : 3115496.36,
    "throughput" : 0.04027709371908852,
    "receivedKBytesPerSec" : 0.04278635963099839,
    "sentKBytesPerSec" : 0.018406341941584258
  },
  "MIT/q/climate%20change-83" : {
    "transaction" : "MIT/q/climate%20change-83",
    "sampleCount" : 127,
    "errorCount" : 60,
    "errorPct" : 47.244095,
    "meanResTime" : 1458.4094488188975,
    "medianResTime" : 283.0,
    "minResTime" : 43.0,
    "maxResTime" : 41133.0,
    "pct1ResTime" : 2356.6000000000004,
    "pct2ResTime" : 5100.599999999999,
    "pct3ResTime" : 39247.19999999999,
    "throughput" : 0.4333642716750382,
    "receivedKBytesPerSec" : 1.2598881218521376,
    "sentKBytesPerSec" : 0.2691598406106683
  },
  "Research/research/-184" : {
    "transaction" : "Research/research/-184",
    "sampleCount" : 104,
    "errorCount" : 21,
    "errorPct" : 20.192308,
    "meanResTime" : 33395.03846153846,
    "medianResTime" : 620.0,
    "minResTime" : 56.0,
    "maxResTime" : 3127056.0,
    "pct1ResTime" : 4603.0,
    "pct2ResTime" : 18621.25,
    "pct3ResTime" : 2974589.9500000086,
    "throughput" : 0.03300513325029157,
    "receivedKBytesPerSec" : 0.3982508667814441,
    "sentKBytesPerSec" : 0.022792062701819247
  },
  "News/sites/default/files/styles/frontpage__featured_news/public/images/202412/MIT-ContextCite.jpg-323" : {
    "transaction" : "News/sites/default/files/styles/frontpage__featured_news/public/images/202412/MIT-ContextCite.jpg-323",
    "sampleCount" : 80,
    "errorCount" : 20,
    "errorPct" : 25.0,
    "meanResTime" : 4381.800000000002,
    "medianResTime" : 2862.0,
    "minResTime" : 97.0,
    "maxResTime" : 42714.0,
    "pct1ResTime" : 9021.100000000013,
    "pct2ResTime" : 20222.20000000001,
    "pct3ResTime" : 42714.0,
    "throughput" : 0.1554795865020397,
    "receivedKBytesPerSec" : 8.214308066645353,
    "sentKBytesPerSec" : 0.10225743605416131
  },
  "News/sites/default/files/styles/frontpage__featured_news/public/images/202412/MIT-Optical-Computation-SampsonWilcox.jpg-343" : {
    "transaction" : "News/sites/default/files/styles/frontpage__featured_news/public/images/202412/MIT-Optical-Computation-SampsonWilcox.jpg-343",
    "sampleCount" : 80,
    "errorCount" : 47,
    "errorPct" : 58.75,
    "meanResTime" : 6405.6124999999965,
    "medianResTime" : 5701.5,
    "minResTime" : 185.0,
    "maxResTime" : 46537.0,
    "pct1ResTime" : 11767.500000000002,
    "pct2ResTime" : 12647.500000000002,
    "pct3ResTime" : 46537.0,
    "throughput" : 0.2767907496531466,
    "receivedKBytesPerSec" : 40.07818216918316,
    "sentKBytesPerSec" : 0.1902936403865383
  },
  "Research/files/images/201806/02_preview.jpeg-217" : {
    "transaction" : "Research/files/images/201806/02_preview.jpeg-217",
    "sampleCount" : 83,
    "errorCount" : 51,
    "errorPct" : 61.44578,
    "meanResTime" : 3576.8674698795166,
    "medianResTime" : 1916.0,
    "minResTime" : 360.0,
    "maxResTime" : 20422.0,
    "pct1ResTime" : 9596.600000000008,
    "pct2ResTime" : 18477.599999999995,
    "pct3ResTime" : 20422.0,
    "throughput" : 0.0994098885291768,
    "receivedKBytesPerSec" : 18.434515364067757,
    "sentKBytesPerSec" : 0.059995421006866466
  },
  "MIT/campus-map/objimgs/object-E52.jpg-126" : {
    "transaction" : "MIT/campus-map/objimgs/object-E52.jpg-126",
    "sampleCount" : 113,
    "errorCount" : 68,
    "errorPct" : 60.17699,
    "meanResTime" : 108506.86725663717,
    "medianResTime" : 662.0,
    "minResTime" : 50.0,
    "maxResTime" : 3080238.0,
    "pct1ResTime" : 8744.600000000006,
    "pct2ResTime" : 12388.899999999972,
    "pct3ResTime" : 3072740.02,
    "throughput" : 0.03585921861175954,
    "receivedKBytesPerSec" : 0.3185892865387984,
    "sentKBytesPerSec" : 0.020436395286162912
  },
  "Research/files/images/201806/brain-waves.jpg-212" : {
    "transaction" : "Research/files/images/201806/brain-waves.jpg-212",
    "sampleCount" : 89,
    "errorCount" : 80,
    "errorPct" : 89.88764,
    "meanResTime" : 97309.12359550563,
    "medianResTime" : 3213.0,
    "minResTime" : 786.0,
    "maxResTime" : 2806615.0,
    "pct1ResTime" : 11842.0,
    "pct2ResTime" : 29764.5,
    "pct3ResTime" : 2806615.0,
    "throughput" : 0.028416909913286915,
    "receivedKBytesPerSec" : 5.0171654649214,
    "sentKBytesPerSec" : 0.016379260421183307
  },
  "Research/research-182" : {
    "transaction" : "Research/research-182",
    "sampleCount" : 109,
    "errorCount" : 58,
    "errorPct" : 53.21101,
    "meanResTime" : 144910.54128440368,
    "medianResTime" : 1469.0,
    "minResTime" : 105.0,
    "maxResTime" : 3061434.0,
    "pct1ResTime" : 18832.0,
    "pct2ResTime" : 1638282.0,
    "pct3ResTime" : 3059912.7,
    "throughput" : 0.03459051337716702,
    "receivedKBytesPerSec" : 0.42900653645665576,
    "sentKBytesPerSec" : 0.046213553122460255
  },
  "Research/files/images/201805/research-2_0.mp4-215" : {
    "transaction" : "Research/files/images/201805/research-2_0.mp4-215",
    "sampleCount" : 85,
    "errorCount" : 17,
    "errorPct" : 20.0,
    "meanResTime" : 69360.69411764706,
    "medianResTime" : 515.0,
    "minResTime" : 85.0,
    "maxResTime" : 3117504.0,
    "pct1ResTime" : 2072.000000000003,
    "pct2ResTime" : 4873.000000000007,
    "pct3ResTime" : 3117504.0,
    "throughput" : 0.02717645866444651,
    "receivedKBytesPerSec" : 0.7047382775144859,
    "sentKBytesPerSec" : 0.01611916193716355
  },
  "News/sites/default/files/styles/frontpage__featured_news/public/images/202412/MIT-AI2050-01-press.jpg-308" : {
    "transaction" : "News/sites/default/files/styles/frontpage__featured_news/public/images/202412/MIT-AI2050-01-press.jpg-308",
    "sampleCount" : 80,
    "errorCount" : 60,
    "errorPct" : 75.0,
    "meanResTime" : 8064.762500000002,
    "medianResTime" : 6879.5,
    "minResTime" : 1194.0,
    "maxResTime" : 28584.0,
    "pct1ResTime" : 14200.100000000002,
    "pct2ResTime" : 20829.05000000001,
    "pct3ResTime" : 28584.0,
    "throughput" : 0.11936788735252471,
    "receivedKBytesPerSec" : 10.214356165985524,
    "sentKBytesPerSec" : 0.07996715890999213
  },
  "MIT/q/climate%20change-79" : {
    "transaction" : "MIT/q/climate%20change-79",
    "sampleCount" : 127,
    "errorCount" : 25,
    "errorPct" : 19.68504,
    "meanResTime" : 352.87401574803147,
    "medianResTime" : 79.0,
    "minResTime" : 43.0,
    "maxResTime" : 5036.0,
    "pct1ResTime" : 796.4000000000004,
    "pct2ResTime" : 1235.7999999999988,
    "pct3ResTime" : 4997.92,
    "throughput" : 0.4335447575221722,
    "receivedKBytesPerSec" : 0.22354651559737004,
    "sentKBytesPerSec" : 0.21846591297015708
  },
  "News/sites/default/files/styles/frontpage__featured_news/public/images/202411/liquid-co2-water-corrosion.png-334" : {
    "transaction" : "News/sites/default/files/styles/frontpage__featured_news/public/images/202411/liquid-co2-water-corrosion.png-334",
    "sampleCount" : 80,
    "errorCount" : 64,
    "errorPct" : 80.0,
    "meanResTime" : 10576.85,
    "medianResTime" : 8486.5,
    "minResTime" : 299.0,
    "maxResTime" : 94796.0,
    "pct1ResTime" : 20448.000000000007,
    "pct2ResTime" : 28909.350000000006,
    "pct3ResTime" : 94796.0,
    "throughput" : 0.19959631644997994,
    "receivedKBytesPerSec" : 35.94845391991572,
    "sentKBytesPerSec" : 0.13338988692244932
  },
  "MIT/q/climate%20chan?count=3-53" : {
    "transaction" : "MIT/q/climate%20chan?count=3-53",
    "sampleCount" : 129,
    "errorCount" : 30,
    "errorPct" : 23.255814,
    "meanResTime" : 1164.77519379845,
    "medianResTime" : 81.0,
    "minResTime" : 43.0,
    "maxResTime" : 74445.0,
    "pct1ResTime" : 1329.0,
    "pct2ResTime" : 4645.0,
    "pct3ResTime" : 55084.19999999927,
    "throughput" : 0.49794837549167575,
    "receivedKBytesPerSec" : 0.2567546311128953,
    "sentKBytesPerSec" : 0.2538369648502488
  },
  "MIT/q/climate%20chan?count=3-54" : {
    "transaction" : "MIT/q/climate%20chan?count=3-54",
    "sampleCount" : 129,
    "errorCount" : 20,
    "errorPct" : 15.503876,
    "meanResTime" : 259.5891472868217,
    "medianResTime" : 79.0,
    "minResTime" : 43.0,
    "maxResTime" : 3192.0,
    "pct1ResTime" : 649.0,
    "pct2ResTime" : 991.5,
    "pct3ResTime" : 3035.099999999994,
    "throughput" : 0.4948671914560604,
    "receivedKBytesPerSec" : 0.2551658955945312,
    "sentKBytesPerSec" : 0.2522662831445933
  },
  "Research/themes/mit/assets/js/main.js-193" : {
    "transaction" : "Research/themes/mit/assets/js/main.js-193",
    "sampleCount" : 98,
    "errorCount" : 91,
    "errorPct" : 92.85714,
    "meanResTime" : 41273.30612244898,
    "medianResTime" : 5483.5,
    "minResTime" : 385.0,
    "maxResTime" : 3050242.0,
    "pct1ResTime" : 23483.800000000014,
    "pct2ResTime" : 32150.599999999944,
    "pct3ResTime" : 3050242.0,
    "throughput" : 0.031113985450719417,
    "receivedKBytesPerSec" : 11.26813700537494,
    "sentKBytesPerSec" : 0.01678168423654376
  },
  "Research/files/images/201805/research-2_0.mp4-216" : {
    "transaction" : "Research/files/images/201805/research-2_0.mp4-216",
    "sampleCount" : 83,
    "errorCount" : 83,
    "errorPct" : 100.0,
    "meanResTime" : 130715.90361445781,
    "medianResTime" : 75894.0,
    "minResTime" : 4436.0,
    "maxResTime" : 2785701.0,
    "pct1ResTime" : 231878.80000000016,
    "pct2ResTime" : 311702.99999999994,
    "pct3ResTime" : 2785701.0,
    "throughput" : 0.02660101237684212,
    "receivedKBytesPerSec" : 82.33582332897569,
    "sentKBytesPerSec" : 0.01593769710388689
  },
  "News/sites/default/files/styles/frontpage__featured_news/public/images/202412/MIT-Community-Policing-01.jpg-337" : {
    "transaction" : "News/sites/default/files/styles/frontpage__featured_news/public/images/202412/MIT-Community-Policing-01.jpg-337",
    "sampleCount" : 80,
    "errorCount" : 53,
    "errorPct" : 66.25,
    "meanResTime" : 6874.624999999997,
    "medianResTime" : 6018.5,
    "minResTime" : 232.0,
    "maxResTime" : 18434.0,
    "pct1ResTime" : 14049.400000000005,
    "pct2ResTime" : 14966.0,
    "pct3ResTime" : 18434.0,
    "throughput" : 0.23663108326752033,
    "receivedKBytesPerSec" : 33.73057660894347,
    "sentKBytesPerSec" : 0.15991084923937895
  },
  "News/sites/default/files/styles/frontpage__featured_news/public/images/202412/MIT_Methane-Conversion-01-PRESS.jpg-336" : {
    "transaction" : "News/sites/default/files/styles/frontpage__featured_news/public/images/202412/MIT_Methane-Conversion-01-PRESS.jpg-336",
    "sampleCount" : 80,
    "errorCount" : 14,
    "errorPct" : 17.5,
    "meanResTime" : 3178.525,
    "medianResTime" : 2813.5,
    "minResTime" : 127.0,
    "maxResTime" : 15058.0,
    "pct1ResTime" : 5638.1,
    "pct2ResTime" : 8670.300000000007,
    "pct3ResTime" : 15058.0,
    "throughput" : 0.22995642325779267,
    "receivedKBytesPerSec" : 15.004451700348097,
    "sentKBytesPerSec" : 0.15674764007220632
  },
  "Research/themes/mit/assets/js/Gallery.65ba9fc3e65cbdd959e3.js-203" : {
    "transaction" : "Research/themes/mit/assets/js/Gallery.65ba9fc3e65cbdd959e3.js-203",
    "sampleCount" : 96,
    "errorCount" : 19,
    "errorPct" : 19.791666,
    "meanResTime" : 2651.989583333334,
    "medianResTime" : 210.0,
    "minResTime" : 47.0,
    "maxResTime" : 129646.0,
    "pct1ResTime" : 2604.2999999999997,
    "pct2ResTime" : 6511.599999999915,
    "pct3ResTime" : 129646.0,
    "throughput" : 0.20311270216061136,
    "receivedKBytesPerSec" : 0.5239412651223754,
    "sentKBytesPerSec" : 0.11286449539716996
  },
  "MIT/q/clima?count=3-43" : {
    "transaction" : "MIT/q/clima?count=3-43",
    "sampleCount" : 130,
    "errorCount" : 26,
    "errorPct" : 20.0,
    "meanResTime" : 294.7076923076924,
    "medianResTime" : 79.0,
    "minResTime" : 42.0,
    "maxResTime" : 2366.0,
    "pct1ResTime" : 688.9000000000002,
    "pct2ResTime" : 1429.3499999999974,
    "pct3ResTime" : 2295.0099999999993,
    "throughput" : 0.4008745231905912,
    "receivedKBytesPerSec" : 0.20670092602014858,
    "sentKBytesPerSec" : 0.20082874062184888
  },
  "Research/files/images/201807/MIT-Brain-Drug-Delivery-03.jpg-188" : {
    "transaction" : "Research/files/images/201807/MIT-Brain-Drug-Delivery-03.jpg-188",
    "sampleCount" : 99,
    "errorCount" : 73,
    "errorPct" : 73.73737,
    "meanResTime" : 5099.414141414142,
    "medianResTime" : 2370.0,
    "minResTime" : 302.0,
    "maxResTime" : 78140.0,
    "pct1ResTime" : 9730.0,
    "pct2ResTime" : 20272.0,
    "pct3ResTime" : 78140.0,
    "throughput" : 0.21707812839184576,
    "receivedKBytesPerSec" : 35.49163802098751,
    "sentKBytesPerSec" : 0.13418989772659995
  },
  "Research/core/modules/views/css/views.module.css-232" : {
    "transaction" : "Research/core/modules/views/css/views.module.css-232",
    "sampleCount" : 80,
    "errorCount" : 2,
    "errorPct" : 2.5,
    "meanResTime" : 308.45000000000005,
    "medianResTime" : 81.0,
    "minResTime" : 45.0,
    "maxResTime" : 6927.0,
    "pct1ResTime" : 443.0,
    "pct2ResTime" : 641.95,
    "pct3ResTime" : 6927.0,
    "throughput" : 0.10040752905856647,
    "receivedKBytesPerSec" : 0.06638271208266551,
    "sentKBytesPerSec" : 0.05932280769573506
  },
  "Research/research/research-alliances/-248" : {
    "transaction" : "Research/research/research-alliances/-248",
    "sampleCount" : 80,
    "errorCount" : 5,
    "errorPct" : 6.25,
    "meanResTime" : 679.6374999999998,
    "medianResTime" : 333.5,
    "minResTime" : 86.0,
    "maxResTime" : 5946.0,
    "pct1ResTime" : 1299.1000000000004,
    "pct2ResTime" : 2479.600000000003,
    "pct3ResTime" : 5946.0,
    "throughput" : 0.10040677293886859,
    "receivedKBytesPerSec" : 0.9881830641385915,
    "sentKBytesPerSec" : 0.0721673680498118
  },
  "MIT/q/cl?count=3-40" : {
    "transaction" : "MIT/q/cl?count=3-40",
    "sampleCount" : 130,
    "errorCount" : 24,
    "errorPct" : 18.461538,
    "meanResTime" : 709.0461538461536,
    "medianResTime" : 78.0,
    "minResTime" : 43.0,
    "maxResTime" : 50695.0,
    "pct1ResTime" : 951.700000000001,
    "pct2ResTime" : 2126.8999999999996,
    "pct3ResTime" : 36189.479999999894,
    "throughput" : 0.4759533712143401,
    "receivedKBytesPerSec" : 0.2454134570323941,
    "sentKBytesPerSec" : 0.237047089179017
  },
  "News/sites/default/files/styles/frontpage__featured_news/public/images/202412/MIT_Smallest-Asteroid-01-PRESS.jpg-306" : {
    "transaction" : "News/sites/default/files/styles/frontpage__featured_news/public/images/202412/MIT_Smallest-Asteroid-01-PRESS.jpg-306",
    "sampleCount" : 80,
    "errorCount" : 57,
    "errorPct" : 71.25,
    "meanResTime" : 10029.500000000002,
    "medianResTime" : 6228.0,
    "minResTime" : 646.0,
    "maxResTime" : 166963.0,
    "pct1ResTime" : 15816.900000000007,
    "pct2ResTime" : 23939.20000000001,
    "pct3ResTime" : 166963.0,
    "throughput" : 0.11571027304731683,
    "receivedKBytesPerSec" : 8.146056896730029,
    "sentKBytesPerSec" : 0.07875982452537093
  },
  "Research/themes/mit/assets/js/modernizr.js-192" : {
    "transaction" : "Research/themes/mit/assets/js/modernizr.js-192",
    "sampleCount" : 98,
    "errorCount" : 18,
    "errorPct" : 18.367348,
    "meanResTime" : 2413.295918367346,
    "medianResTime" : 535.5,
    "minResTime" : 48.0,
    "maxResTime" : 72709.0,
    "pct1ResTime" : 3870.7000000000085,
    "pct2ResTime" : 9593.249999999973,
    "pct3ResTime" : 72709.0,
    "throughput" : 0.21503913492828006,
    "receivedKBytesPerSec" : 1.2908648070352906,
    "sentKBytesPerSec" : 0.11822952437951335
  },
  "Research/themes/mit/assets/js/lazysizes-unveilhooks.3bbadeef1592cbebc3d2.js-207" : {
    "transaction" : "Research/themes/mit/assets/js/lazysizes-unveilhooks.3bbadeef1592cbebc3d2.js-207",
    "sampleCount" : 97,
    "errorCount" : 20,
    "errorPct" : 20.618557,
    "meanResTime" : 33278.40206185567,
    "medianResTime" : 504.0,
    "minResTime" : 55.0,
    "maxResTime" : 3095999.0,
    "pct1ResTime" : 2551.0,
    "pct2ResTime" : 5113.399999999978,
    "pct3ResTime" : 3095999.0,
    "throughput" : 0.030800642050497175,
    "receivedKBytesPerSec" : 0.253877690690109,
    "sentKBytesPerSec" : 0.017533741785833928
  },
  "MIT/q/climate?count=3-45" : {
    "transaction" : "MIT/q/climate?count=3-45",
    "sampleCount" : 130,
    "errorCount" : 23,
    "errorPct" : 17.692308,
    "meanResTime" : 1689.9307692307693,
    "medianResTime" : 79.0,
    "minResTime" : 42.0,
    "maxResTime" : 141606.0,
    "pct1ResTime" : 1014.9,
    "pct2ResTime" : 2250.399999999996,
    "pct3ResTime" : 103633.78999999972,
    "throughput" : 0.5843116808399705,
    "receivedKBytesPerSec" : 0.3012857104331098,
    "sentKBytesPerSec" : 0.2938676910474461
  },
  "Research/files/images/201806/rna-imaging.jpg-221" : {
    "transaction" : "Research/files/images/201806/rna-imaging.jpg-221",
    "sampleCount" : 82,
    "errorCount" : 77,
    "errorPct" : 93.902435,
    "meanResTime" : 74752.63414634146,
    "medianResTime" : 3679.5,
    "minResTime" : 564.0,
    "maxResTime" : 2926118.0,
    "pct1ResTime" : 13261.100000000006,
    "pct2ResTime" : 18670.249999999993,
    "pct3ResTime" : 2926118.0,
    "throughput" : 0.02645098149269985,
    "receivedKBytesPerSec" : 8.741867306030436,
    "sentKBytesPerSec" : 0.015574225002370911
  },
  "MIT/themes/mit/assets/favicon/favicon.svg-12" : {
    "transaction" : "MIT/themes/mit/assets/favicon/favicon.svg-12",
    "sampleCount" : 136,
    "errorCount" : 39,
    "errorPct" : 28.67647,
    "meanResTime" : 46031.01470588235,
    "medianResTime" : 82.0,
    "minResTime" : 46.0,
    "maxResTime" : 3074806.0,
    "pct1ResTime" : 1160.2999999999997,
    "pct2ResTime" : 4267.250000000001,
    "pct3ResTime" : 3070818.88,
    "throughput" : 0.04309634568339397,
    "receivedKBytesPerSec" : 0.039520250133091656,
    "sentKBytesPerSec" : 0.02533655651483655
  },
  "News/sites/default/files/styles/frontpage__featured_news/public/images/202411/lab-coat-ceremony.png-335" : {
    "transaction" : "News/sites/default/files/styles/frontpage__featured_news/public/images/202411/lab-coat-ceremony.png-335",
    "sampleCount" : 80,
    "errorCount" : 61,
    "errorPct" : 76.25,
    "meanResTime" : 8935.225,
    "medianResTime" : 8075.0,
    "minResTime" : 346.0,
    "maxResTime" : 45121.0,
    "pct1ResTime" : 15334.600000000006,
    "pct2ResTime" : 22027.150000000012,
    "pct3ResTime" : 45121.0,
    "throughput" : 0.18986410476701301,
    "receivedKBytesPerSec" : 29.428590905005056,
    "sentKBytesPerSec" : 0.12682328873109072
  },
  "News/sites/default/files/styles/frontpage__featured_news/public/images/202412/MIT-Health-and-Life-Science_01-press.jpg-322" : {
    "transaction" : "News/sites/default/files/styles/frontpage__featured_news/public/images/202412/MIT-Health-and-Life-Science_01-press.jpg-322",
    "sampleCount" : 80,
    "errorCount" : 56,
    "errorPct" : 70.0,
    "meanResTime" : 7393.85,
    "medianResTime" : 6455.0,
    "minResTime" : 162.0,
    "maxResTime" : 22878.0,
    "pct1ResTime" : 13484.300000000001,
    "pct2ResTime" : 16343.650000000003,
    "pct3ResTime" : 22878.0,
    "throughput" : 0.15538053664552845,
    "receivedKBytesPerSec" : 18.875120025395006,
    "sentKBytesPerSec" : 0.1066723801384829
  },
  "News/sites/default/files/styles/frontpage__featured_news/public/images/202411/social-media-study.jpg-330" : {
    "transaction" : "News/sites/default/files/styles/frontpage__featured_news/public/images/202411/social-media-study.jpg-330",
    "sampleCount" : 80,
    "errorCount" : 2,
    "errorPct" : 2.5,
    "meanResTime" : 1898.3999999999994,
    "medianResTime" : 1737.0,
    "minResTime" : 104.0,
    "maxResTime" : 6849.0,
    "pct1ResTime" : 3427.3,
    "pct2ResTime" : 4418.85,
    "pct3ResTime" : 6849.0,
    "throughput" : 0.15706292333366056,
    "receivedKBytesPerSec" : 4.85010767399627,
    "sentKBytesPerSec" : 0.10506650633159909
  },
  "MIT/search-39-0" : {
    "transaction" : "MIT/search-39-0",
    "sampleCount" : 133,
    "errorCount" : 0,
    "errorPct" : 0.0,
    "meanResTime" : 678.3233082706771,
    "medianResTime" : 81.0,
    "minResTime" : 45.0,
    "maxResTime" : 27138.0,
    "pct1ResTime" : 1017.8000000000002,
    "pct2ResTime" : 2287.2,
    "pct3ResTime" : 21067.63999999994,
    "throughput" : 0.9408202821046079,
    "receivedKBytesPerSec" : 0.6642705702750307,
    "sentKBytesPerSec" : 0.6633518004682879
  },
  "Research/files/images/201806/12_preview.jpeg-214" : {
    "transaction" : "Research/files/images/201806/12_preview.jpeg-214",
    "sampleCount" : 83,
    "errorCount" : 51,
    "errorPct" : 61.44578,
    "meanResTime" : 3757.0120481927715,
    "medianResTime" : 1752.0,
    "minResTime" : 406.0,
    "maxResTime" : 37987.0,
    "pct1ResTime" : 9301.6,
    "pct2ResTime" : 13692.399999999996,
    "pct3ResTime" : 37987.0,
    "throughput" : 0.09908767707445423,
    "receivedKBytesPerSec" : 20.228981511492975,
    "sentKBytesPerSec" : 0.05980096135938742
  },
  "News/sites/default/files/styles/frontpage__featured_news/public/images/202412/MIT-car-aerodynamics-01-press.jpg-333" : {
    "transaction" : "News/sites/default/files/styles/frontpage__featured_news/public/images/202412/MIT-car-aerodynamics-01-press.jpg-333",
    "sampleCount" : 80,
    "errorCount" : 39,
    "errorPct" : 48.75,
    "meanResTime" : 5925.4375,
    "medianResTime" : 4757.0,
    "minResTime" : 189.0,
    "maxResTime" : 90095.0,
    "pct1ResTime" : 9747.400000000001,
    "pct2ResTime" : 10748.050000000001,
    "pct3ResTime" : 90095.0,
    "throughput" : 0.15888210550566215,
    "receivedKBytesPerSec" : 12.604149237216943,
    "sentKBytesPerSec" : 0.10799018108587975
  },
  "Research/files/images/201806/7257183044_f524688650_b_0.jpg-213" : {
    "transaction" : "Research/files/images/201806/7257183044_f524688650_b_0.jpg-213",
    "sampleCount" : 86,
    "errorCount" : 50,
    "errorPct" : 58.139534,
    "meanResTime" : 35736.732558139534,
    "medianResTime" : 1540.0,
    "minResTime" : 390.0,
    "maxResTime" : 2781492.0,
    "pct1ResTime" : 6768.9,
    "pct2ResTime" : 8475.799999999994,
    "pct3ResTime" : 2781492.0,
    "throughput" : 0.02747158846793826,
    "receivedKBytesPerSec" : 6.27793676870871,
    "sentKBytesPerSec" : 0.016757968437700346
  },
  "MIT/search-39-1" : {
    "transaction" : "MIT/search-39-1",
    "sampleCount" : 133,
    "errorCount" : 1,
    "errorPct" : 0.7518797,
    "meanResTime" : 26652.045112781954,
    "medianResTime" : 531.0,
    "minResTime" : 51.0,
    "maxResTime" : 3094032.0,
    "pct1ResTime" : 4750.400000000001,
    "pct2ResTime" : 19094.3,
    "pct3ResTime" : 2067749.1399999897,
    "throughput" : 0.04215051282595736,
    "receivedKBytesPerSec" : 0.3890522787977533,
    "sentKBytesPerSec" : 0.02953680349842918
  },
  "Research/files/images/201806/04_preview.jpeg-219" : {
    "transaction" : "Research/files/images/201806/04_preview.jpeg-219",
    "sampleCount" : 80,
    "errorCount" : 47,
    "errorPct" : 58.75,
    "meanResTime" : 2376.475000000001,
    "medianResTime" : 1597.0,
    "minResTime" : 322.0,
    "maxResTime" : 10129.0,
    "pct1ResTime" : 4866.500000000003,
    "pct2ResTime" : 7327.050000000003,
    "pct3ResTime" : 10129.0,
    "throughput" : 0.09844166838939586,
    "receivedKBytesPerSec" : 18.54577583724639,
    "sentKBytesPerSec" : 0.05941108502406899
  },
  "Total" : {
    "transaction" : "Total",
    "sampleCount" : 9808,
    "errorCount" : 4287,
    "errorPct" : 43.709217,
    "meanResTime" : 29398.764579934734,
    "medianResTime" : 1203.5,
    "minResTime" : 42.0,
    "maxResTime" : 3144320.0,
    "pct1ResTime" : 12109.500000000002,
    "pct2ResTime" : 20306.649999999983,
    "pct3ResTime" : 328863.5599999998,
    "throughput" : 3.107682070943109,
    "receivedKBytesPerSec" : 394.79311715049266,
    "sentKBytesPerSec" : 1.9425525478842223
  },
  "News/sites/default/files/images/202412/shass-thumb.jpg-314" : {
    "transaction" : "News/sites/default/files/images/202412/shass-thumb.jpg-314",
    "sampleCount" : 80,
    "errorCount" : 75,
    "errorPct" : 93.75,
    "meanResTime" : 16536.212499999987,
    "medianResTime" : 14981.5,
    "minResTime" : 994.0,
    "maxResTime" : 94264.0,
    "pct1ResTime" : 23779.0,
    "pct2ResTime" : 39006.40000000001,
    "pct3ResTime" : 94264.0,
    "throughput" : 0.13897888736977243,
    "receivedKBytesPerSec" : 26.76987170077151,
    "sentKBytesPerSec" : 0.08482598106065213
  },
  "Research/themes/mit/assets/js/PauseVideo.44487d0c747ba929687f.js-204" : {
    "transaction" : "Research/themes/mit/assets/js/PauseVideo.44487d0c747ba929687f.js-204",
    "sampleCount" : 97,
    "errorCount" : 19,
    "errorPct" : 19.58763,
    "meanResTime" : 1262.463917525773,
    "medianResTime" : 195.0,
    "minResTime" : 43.0,
    "maxResTime" : 14637.0,
    "pct1ResTime" : 3748.2000000000003,
    "pct2ResTime" : 7723.599999999993,
    "pct3ResTime" : 14637.0,
    "throughput" : 0.20602265824451704,
    "receivedKBytesPerSec" : 0.30883279336458364,
    "sentKBytesPerSec" : 0.11629013326692465
  }
}